{"cameraMode":{"drawMode":0,"name":"Shaded","section":"Shading Mode"},"sceneLighting":true,"audioPlay":false,"sceneViewState":{"m_AlwaysRefresh":false,"showFog":true,"showSkybox":true,"showFlares":true,"showImageEffects":true,"showParticleSystems":true,"showVisualEffectGraphs":true,"m_FxEnabled":true},"in2DMode":false,"pivot":{"x":-3.4695684909820558,"y":-2.352510690689087,"z":6.290957927703857},"rotation":{"x":-0.4462355375289917,"y":-0.17064613103866578,"z":0.0871218740940094,"w":-0.8741227984428406},"size":8.221464157104493,"orthographic":false}