{"cameraMode":{"drawMode":0,"name":"Shaded","section":"Shading Mode"},"sceneLighting":true,"audioPlay":false,"sceneViewState":{"m_AlwaysRefresh":false,"showFog":true,"showSkybox":true,"showFlares":true,"showImageEffects":true,"showParticleSystems":true,"showVisualEffectGraphs":true,"m_FxEnabled":true},"in2DMode":false,"pivot":{"x":0.27920836210250857,"y":-5.366875171661377,"z":11.07729434967041},"rotation":{"x":-0.24672386050224305,"y":-0.01104986947029829,"z":0.002815757878124714,"w":-0.9690380096435547},"size":13.016897201538086,"orthographic":false}